lab01/Ex2_FullAdder/full_adder.v
module full_adder (a, b, cin, sum, cout);
    input a, b, cin;
    output sum, cout;
    
    wire a, b, cin;
    wire sum, cout;

    assign sum = a ^ b ^ cin;
    assign cout = (a & b) | (a & cin) | (b & cin);

endmodule

labs/lab01/Ex2_FullAdder/tb_full_adder.v


module tb_full_adder;

    // Inputs
    reg a;
    reg b;
    reg cin;

    // Outputs
    wire sum;
    wire cout;

    // Instantiate the Device Under Test (DUT)
    full_adder dut (
        .a(a),
        .b(b),
        .cin(cin),
        .sum(sum),
        .cout(cout)
    );

    // Testbench logic
    initial begin
        $dumpfile("full_adder.vcd");    // Specify the name of the VCD file
        $dumpvars(0, tb_full_adder);    // Dump all variables in the testbench

        // Initialize inputs
        a = 0;
        b = 0;
        cin = 0;

        // Apply test cases
        a = 0; b = 0; cin = 0; #10;  // Wait 10 time units
        a = 0; b = 0; cin = 1; #10;
        a = 0; b = 1; cin = 0; #10;
        a = 0; b = 1; cin = 1; #10;
        a = 1; b = 0; cin = 0; #10;
        a = 1; b = 0; cin = 1; #10;
        a = 1; b = 1; cin = 0; #10;
        a = 1; b = 1; cin = 1; #10;
        // End simulation
        $finish;
    end
endmodule

lab01/Ex2_FullAdder/full_adder.vcd
$date
	Wed Mar  5 16:06:51 2025
$end
$version
	Icarus Verilog
$end
$timescale
	1s
$end
$scope module tb_full_adder $end
$var wire 1 ! sum $end
$var wire 1 " cout $end
$var reg 1 # a $end
$var reg 1 $ b $end
$var reg 1 % cin $end
$scope module dut $end
$var wire 1 # a $end
$var wire 1 $ b $end
$var wire 1 % cin $end
$var wire 1 " cout $end
$var wire 1 ! sum $end
$upscope $end
$upscope $end
$enddefinitions $end
$comment Show the parameter values. $end
$dumpall
$end
#0
$dumpvars
0%
0$
0#
0"
0!
$end
#10
1!
1%
#20
0%
1$
#30
1"
0!
1%
#40
0"
1!
0%
0$
1#
#50
1"
0!
1%
#60
0%
1$
#70
1!
1%
